[
    {
        "id": "599d34db.077b0c",
        "type": "tab",
        "label": "HTTP Gen QR",
        "disabled": false,
        "info": ""
    },
    {
        "id": "e46ff4fb.d77fc8",
        "type": "modbus-client",
        "name": "",
        "clienttype": "tcp",
        "bufferCommands": true,
        "stateLogEnabled": false,
        "queueLogEnabled": false,
        "tcpHost": "127.0.0.1",
        "tcpPort": "10502",
        "tcpType": "DEFAULT",
        "serialPort": "/dev/ttyUSB",
        "serialType": "RTU-BUFFERD",
        "serialBaudrate": "9600",
        "serialDatabits": "8",
        "serialStopbits": "1",
        "serialParity": "none",
        "serialConnectionDelay": "100",
        "unit_id": "1",
        "commandDelay": "1",
        "clientTimeout": "1000",
        "reconnectOnTimeout": true,
        "reconnectTimeout": "2000",
        "parallelUnitIdsAllowed": true
    },
    {
        "id": "211d2f3b.1c226",
        "type": "modbus-client",
        "name": "PLC",
        "clienttype": "tcp",
        "bufferCommands": true,
        "stateLogEnabled": false,
        "queueLogEnabled": false,
        "tcpHost": "192.168.2.10",
        "tcpPort": "502",
        "tcpType": "DEFAULT",
        "serialPort": "/dev/ttyUSB",
        "serialType": "RTU-BUFFERD",
        "serialBaudrate": "9600",
        "serialDatabits": "8",
        "serialStopbits": "1",
        "serialParity": "none",
        "serialConnectionDelay": "100",
        "unit_id": 1,
        "commandDelay": 1,
        "clientTimeout": 1000,
        "reconnectOnTimeout": true,
        "reconnectTimeout": 2000,
        "parallelUnitIdsAllowed": true
    },
    {
        "id": "618d5f4c.a95f",
        "type": "ui_tab",
        "name": "Home",
        "icon": "dashboard"
    },
    {
        "id": "890778c.fdea288",
        "type": "ui_group",
        "name": "Default",
        "tab": "618d5f4c.a95f",
        "order": 1,
        "disp": true,
        "width": "6",
        "collapse": false
    },
    {
        "id": "d8835bff.8c58b8",
        "type": "ui_base",
        "theme": {
            "name": "theme-dark",
            "lightTheme": {
                "default": "#0094CE",
                "baseColor": "#0094CE",
                "baseFont": "-apple-system,BlinkMacSystemFont,Segoe UI,Roboto,Oxygen-Sans,Ubuntu,Cantarell,Helvetica Neue,sans-serif",
                "edited": true,
                "reset": false
            },
            "darkTheme": {
                "default": "#097479",
                "baseColor": "#097479",
                "baseFont": "-apple-system,BlinkMacSystemFont,Segoe UI,Roboto,Oxygen-Sans,Ubuntu,Cantarell,Helvetica Neue,sans-serif",
                "edited": true,
                "reset": false
            },
            "customTheme": {
                "name": "Untitled Theme 1",
                "default": "#4B7930",
                "baseColor": "#4B7930",
                "baseFont": "-apple-system,BlinkMacSystemFont,Segoe UI,Roboto,Oxygen-Sans,Ubuntu,Cantarell,Helvetica Neue,sans-serif"
            },
            "themeState": {
                "base-color": {
                    "default": "#097479",
                    "value": "#097479",
                    "edited": false
                },
                "page-titlebar-backgroundColor": {
                    "value": "#097479",
                    "edited": false
                },
                "page-backgroundColor": {
                    "value": "#111111",
                    "edited": false
                },
                "page-sidebar-backgroundColor": {
                    "value": "#333333",
                    "edited": false
                },
                "group-textColor": {
                    "value": "#0eb8c0",
                    "edited": false
                },
                "group-borderColor": {
                    "value": "#555555",
                    "edited": false
                },
                "group-backgroundColor": {
                    "value": "#333333",
                    "edited": false
                },
                "widget-textColor": {
                    "value": "#eeeeee",
                    "edited": false
                },
                "widget-backgroundColor": {
                    "value": "#097479",
                    "edited": false
                },
                "widget-borderColor": {
                    "value": "#333333",
                    "edited": false
                },
                "base-font": {
                    "value": "-apple-system,BlinkMacSystemFont,Segoe UI,Roboto,Oxygen-Sans,Ubuntu,Cantarell,Helvetica Neue,sans-serif"
                }
            },
            "angularTheme": {
                "primary": "indigo",
                "accents": "blue",
                "warn": "red",
                "background": "grey"
            }
        },
        "site": {
            "name": "Node-RED Dashboard",
            "hideToolbar": "false",
            "allowSwipe": "false",
            "lockMenu": "false",
            "allowTempTheme": "true",
            "dateFormat": "DD/MM/YYYY",
            "sizes": {
                "sx": 48,
                "sy": 48,
                "gx": 6,
                "gy": 6,
                "cx": 6,
                "cy": 6,
                "px": 0,
                "py": 0
            }
        }
    },
    {
        "id": "4f4e163.0866ae8",
        "type": "http in",
        "z": "599d34db.077b0c",
        "name": "",
        "url": "qr",
        "method": "get",
        "upload": false,
        "swaggerDoc": "",
        "x": 1070,
        "y": 240,
        "wires": [
            [
                "ab643fdc.d56f5"
            ]
        ]
    },
    {
        "id": "8fb185a6.214bc8",
        "type": "http response",
        "z": "599d34db.077b0c",
        "name": "",
        "statusCode": "200",
        "headers": {
            "content-type": "text/html"
        },
        "x": 1940,
        "y": 240,
        "wires": []
    },
    {
        "id": "19cd9325.f7972d",
        "type": "qrcode-generator",
        "z": "599d34db.077b0c",
        "name": "",
        "qrtype": "text2qr",
        "text2qrText": "qrcodeinput",
        "ssid": "",
        "hiddenssid": false,
        "wifitype": "",
        "phonenum": "",
        "smsphonenum": "",
        "smstext": "",
        "mailto": "",
        "mailsubject": "",
        "mailbody": "",
        "latitude": "",
        "longitude": "",
        "colorlight": "#ffffff",
        "colordark": "#000000",
        "printstatus": true,
        "x": 1850,
        "y": 60,
        "wires": [
            [
                "2314d29.97efd2e"
            ]
        ]
    },
    {
        "id": "2314d29.97efd2e",
        "type": "template",
        "z": "599d34db.077b0c",
        "name": "",
        "field": "payload",
        "fieldType": "msg",
        "format": "handlebars",
        "syntax": "mustache",
        "template": "<img src=\"{{{payload}}}\">",
        "output": "str",
        "x": 2100,
        "y": 140,
        "wires": [
            [
                "4c32450a.29ab1c",
                "8fb185a6.214bc8"
            ]
        ]
    },
    {
        "id": "24c4e47f.4baa2c",
        "type": "inject",
        "z": "599d34db.077b0c",
        "name": "",
        "props": [
            {
                "p": "payload"
            },
            {
                "p": "topic",
                "vt": "str"
            }
        ],
        "repeat": "",
        "crontab": "",
        "once": false,
        "onceDelay": 0.1,
        "topic": "",
        "payload": "",
        "payloadType": "date",
        "x": 160,
        "y": 140,
        "wires": [
            [
                "e290bf37.87cdb"
            ]
        ]
    },
    {
        "id": "5de148f6.cc0458",
        "type": "debug",
        "z": "599d34db.077b0c",
        "name": "",
        "active": true,
        "tosidebar": true,
        "console": false,
        "tostatus": false,
        "complete": "true",
        "targetType": "full",
        "statusVal": "",
        "statusType": "auto",
        "x": 770,
        "y": 80,
        "wires": []
    },
    {
        "id": "e290bf37.87cdb",
        "type": "function",
        "z": "599d34db.077b0c",
        "name": "",
        "func": "msg.payload = { \n    'fc': 3,\n    'unitid': 1, \n    'address': 0,\n    'quantity': 7\n} \n return msg\n\n",
        "outputs": 1,
        "noerr": 0,
        "initialize": "",
        "finalize": "",
        "x": 400,
        "y": 140,
        "wires": [
            [
                "be3e7202.e1761"
            ]
        ]
    },
    {
        "id": "be3e7202.e1761",
        "type": "modbus-flex-getter",
        "z": "599d34db.077b0c",
        "name": "",
        "showStatusActivities": false,
        "showErrors": false,
        "logIOActivities": false,
        "server": "211d2f3b.1c226",
        "useIOFile": false,
        "ioFile": "",
        "useIOForPayload": false,
        "emptyMsgOnFail": false,
        "keepMsgProperties": false,
        "x": 610,
        "y": 140,
        "wires": [
            [],
            [
                "c7ef0b36.bbe1e8",
                "5de148f6.cc0458"
            ]
        ]
    },
    {
        "id": "c7ef0b36.bbe1e8",
        "type": "modbus-response",
        "z": "599d34db.077b0c",
        "name": "",
        "registerShowMax": 20,
        "x": 850,
        "y": 140,
        "wires": []
    },
    {
        "id": "88a3ede3.5cac2",
        "type": "inject",
        "z": "599d34db.077b0c",
        "name": "",
        "props": [
            {
                "p": "payload"
            },
            {
                "p": "topic",
                "vt": "str"
            }
        ],
        "repeat": "",
        "crontab": "",
        "once": false,
        "onceDelay": 0.1,
        "topic": "",
        "payload": "",
        "payloadType": "date",
        "x": 180,
        "y": 240,
        "wires": [
            [
                "6bba894.e817d78"
            ]
        ]
    },
    {
        "id": "6bba894.e817d78",
        "type": "function",
        "z": "599d34db.077b0c",
        "name": "",
        "func": "msg.payload = { \n    'value': -222, \n    'fc': 6,\n    'unitid': 1, \n    'address': 0,\n    'quantity': 6\n} \n return msg\n\n",
        "outputs": 1,
        "noerr": 0,
        "initialize": "",
        "finalize": "",
        "x": 320,
        "y": 240,
        "wires": [
            [
                "4bce298c.6089b8"
            ]
        ]
    },
    {
        "id": "4bce298c.6089b8",
        "type": "modbus-flex-write",
        "z": "599d34db.077b0c",
        "name": "",
        "showStatusActivities": false,
        "showErrors": false,
        "server": "211d2f3b.1c226",
        "emptyMsgOnFail": false,
        "keepMsgProperties": false,
        "x": 510,
        "y": 260,
        "wires": [
            [],
            []
        ]
    },
    {
        "id": "1bc0ccae.4f1563",
        "type": "inject",
        "z": "599d34db.077b0c",
        "name": "",
        "props": [
            {
                "p": "payload"
            },
            {
                "p": "topic",
                "vt": "str"
            }
        ],
        "repeat": "",
        "crontab": "",
        "once": false,
        "onceDelay": 0.1,
        "topic": "",
        "payload": "",
        "payloadType": "date",
        "x": 1100,
        "y": 480,
        "wires": [
            [
                "13228094.fb512f"
            ]
        ]
    },
    {
        "id": "96745d8d.5eacf",
        "type": "switch",
        "z": "599d34db.077b0c",
        "name": "",
        "property": "payload",
        "propertyType": "msg",
        "rules": [
            {
                "t": "eq",
                "v": "false",
                "vt": "str"
            },
            {
                "t": "eq",
                "v": "true",
                "vt": "str"
            }
        ],
        "checkall": "true",
        "repair": false,
        "outputs": 2,
        "x": 1490,
        "y": 480,
        "wires": [
            [
                "581f18da.c43fc8",
                "88a1b7e7.0c1cb8"
            ],
            [
                "581f18da.c43fc8",
                "d184220d.fa5f9"
            ]
        ]
    },
    {
        "id": "ac385043.6cd6e",
        "type": "modbus-flex-write",
        "z": "599d34db.077b0c",
        "name": "No internet",
        "showStatusActivities": false,
        "showErrors": false,
        "server": "211d2f3b.1c226",
        "emptyMsgOnFail": false,
        "keepMsgProperties": false,
        "x": 2030,
        "y": 460,
        "wires": [
            [],
            []
        ]
    },
    {
        "id": "99297d47.31b18",
        "type": "modbus-flex-write",
        "z": "599d34db.077b0c",
        "name": "Internet",
        "showStatusActivities": false,
        "showErrors": false,
        "server": "211d2f3b.1c226",
        "emptyMsgOnFail": false,
        "keepMsgProperties": false,
        "x": 2140,
        "y": 540,
        "wires": [
            [],
            []
        ]
    },
    {
        "id": "581f18da.c43fc8",
        "type": "debug",
        "z": "599d34db.077b0c",
        "name": "",
        "active": true,
        "tosidebar": true,
        "console": false,
        "tostatus": false,
        "complete": "true",
        "targetType": "full",
        "statusVal": "",
        "statusType": "auto",
        "x": 1770,
        "y": 400,
        "wires": []
    },
    {
        "id": "8498208b.d7b31",
        "type": "inject",
        "z": "599d34db.077b0c",
        "name": "",
        "props": [
            {
                "p": "payload"
            },
            {
                "p": "topic",
                "vt": "str"
            }
        ],
        "repeat": "",
        "crontab": "",
        "once": false,
        "onceDelay": 0.1,
        "topic": "",
        "payload": "{\"0\":\"A\",\"1\":\"B\",\"2\":\"C\",\"3\":\"D\",\"4\":\"E\",\"5\":\"F\",\"6\":\"17\",\"7\":\"0,23\"}",
        "payloadType": "json",
        "x": 1290,
        "y": 120,
        "wires": [
            [
                "c1bc543a.b447b8"
            ]
        ]
    },
    {
        "id": "c1bc543a.b447b8",
        "type": "function",
        "z": "599d34db.077b0c",
        "name": "",
        "func": "var d = msg.payload.data;\nvar mac = `${d[0]}-${d[1]}-${d[2]}-${d[3]}-${d[4]}-${d[5]}`;\n\nvar newMsg = {test: mac}\nnode.send(newMsg);",
        "outputs": 1,
        "noerr": 0,
        "initialize": "",
        "finalize": "",
        "x": 1540,
        "y": 120,
        "wires": [
            []
        ]
    },
    {
        "id": "ab643fdc.d56f5",
        "type": "function",
        "z": "599d34db.077b0c",
        "name": "",
        "func": "msg.payload = { \n    'fc': 3,\n    'unitid': 1, \n    'address': 0,\n    'quantity': 8\n} \nnode.send(msg);\n",
        "outputs": 1,
        "noerr": 0,
        "initialize": "",
        "finalize": "",
        "x": 1240,
        "y": 260,
        "wires": [
            [
                "242bda9e.c2dc96"
            ]
        ]
    },
    {
        "id": "242bda9e.c2dc96",
        "type": "modbus-flex-getter",
        "z": "599d34db.077b0c",
        "name": "",
        "showStatusActivities": false,
        "showErrors": false,
        "logIOActivities": false,
        "server": "211d2f3b.1c226",
        "useIOFile": false,
        "ioFile": "",
        "useIOForPayload": false,
        "emptyMsgOnFail": true,
        "keepMsgProperties": true,
        "x": 1410,
        "y": 240,
        "wires": [
            [],
            [
                "5fc00fa1.bf9a8"
            ]
        ]
    },
    {
        "id": "5fc00fa1.bf9a8",
        "type": "template",
        "z": "599d34db.077b0c",
        "name": "",
        "field": "qrcodeinput",
        "fieldType": "msg",
        "format": "handlebars",
        "syntax": "mustache",
        "template": "{{payload.data}}",
        "output": "str",
        "x": 1660,
        "y": 200,
        "wires": [
            [
                "19cd9325.f7972d",
                "bc75c3b2.aa31b"
            ]
        ]
    },
    {
        "id": "88a1b7e7.0c1cb8",
        "type": "function",
        "z": "599d34db.077b0c",
        "name": "",
        "func": "msg.payload = { \n    'value': false, \n    'fc': 6,\n    'unitid': 1, \n    'address': 0,\n    'quantity': 20\n} \n return msg\n\n",
        "outputs": 1,
        "noerr": 0,
        "initialize": "",
        "finalize": "",
        "x": 1800,
        "y": 460,
        "wires": [
            [
                "ac385043.6cd6e"
            ]
        ]
    },
    {
        "id": "d184220d.fa5f9",
        "type": "function",
        "z": "599d34db.077b0c",
        "name": "",
        "func": "msg.payload = { \n    'value': true, \n    'fc': 6,\n    'unitid': 1, \n    'address': 0,\n    'quantity': 20\n} \n return msg\n\n",
        "outputs": 1,
        "noerr": 0,
        "initialize": "",
        "finalize": "",
        "x": 1800,
        "y": 520,
        "wires": [
            [
                "99297d47.31b18"
            ]
        ]
    },
    {
        "id": "13228094.fb512f",
        "type": "is online",
        "z": "599d34db.077b0c",
        "name": "",
        "url": "www.google.dk",
        "action": "0",
        "x": 1320,
        "y": 480,
        "wires": [
            [
                "96745d8d.5eacf"
            ]
        ]
    },
    {
        "id": "e1fc2846.d3dae8",
        "type": "http response",
        "z": "599d34db.077b0c",
        "name": "",
        "statusCode": "200",
        "headers": {
            "content-type": "text/html"
        },
        "x": 800,
        "y": 280,
        "wires": []
    },
    {
        "id": "2974e7b8.2af778",
        "type": "http in",
        "z": "599d34db.077b0c",
        "name": "",
        "url": "/test",
        "method": "get",
        "upload": false,
        "swaggerDoc": "",
        "x": 830,
        "y": 380,
        "wires": [
            [
                "e1fc2846.d3dae8"
            ]
        ]
    },
    {
        "id": "4c32450a.29ab1c",
        "type": "debug",
        "z": "599d34db.077b0c",
        "name": "",
        "active": true,
        "tosidebar": true,
        "console": false,
        "tostatus": false,
        "complete": "false",
        "statusVal": "",
        "statusType": "auto",
        "x": 2270,
        "y": 80,
        "wires": []
    },
    {
        "id": "bc75c3b2.aa31b",
        "type": "debug",
        "z": "599d34db.077b0c",
        "name": "",
        "active": true,
        "tosidebar": true,
        "console": false,
        "tostatus": false,
        "complete": "false",
        "statusVal": "",
        "statusType": "auto",
        "x": 1860,
        "y": 180,
        "wires": []
    }
]